<annotation>
	<folder>images</folder>
	<filename>115.jpg</filename>
	<path>/home/ragnarock/Music/hong/data/images/115.jpg</path>
	<source>
		<database>Unknown</database>
	</source>
	<size>
		<width>275</width>
		<height>183</height>
		<depth>3</depth>
	</size>
	<segmented>0</segmented>
	<object>
		<name>head</name>
		<pose>Unspecified</pose>
		<truncated>0</truncated>
		<difficult>0</difficult>
		<bndbox>
			<xmin>81</xmin>
			<ymin>93</ymin>
			<xmax>94</xmax>
			<ymax>106</ymax>
		</bndbox>
	</object>
	<object>
		<name>head</name>
		<pose>Unspecified</pose>
		<truncated>0</truncated>
		<difficult>0</difficult>
		<bndbox>
			<xmin>118</xmin>
			<ymin>96</ymin>
			<xmax>141</xmax>
			<ymax>119</ymax>
		</bndbox>
	</object>
	<object>
		<name>head</name>
		<pose>Unspecified</pose>
		<truncated>0</truncated>
		<difficult>0</difficult>
		<bndbox>
			<xmin>158</xmin>
			<ymin>97</ymin>
			<xmax>170</xmax>
			<ymax>109</ymax>
		</bndbox>
	</object>
</annotation>
