<annotation>
	<folder>images</folder>
	<filename>148.jpg</filename>
	<path>/home/ragnarock/Music/hong/data/images/148.jpg</path>
	<source>
		<database>Unknown</database>
	</source>
	<size>
		<width>194</width>
		<height>259</height>
		<depth>3</depth>
	</size>
	<segmented>0</segmented>
	<object>
		<name>head</name>
		<pose>Unspecified</pose>
		<truncated>0</truncated>
		<difficult>0</difficult>
		<bndbox>
			<xmin>102</xmin>
			<ymin>67</ymin>
			<xmax>190</xmax>
			<ymax>187</ymax>
		</bndbox>
	</object>
	<object>
		<name>head</name>
		<pose>Unspecified</pose>
		<truncated>0</truncated>
		<difficult>0</difficult>
		<bndbox>
			<xmin>6</xmin>
			<ymin>106</ymin>
			<xmax>22</xmax>
			<ymax>129</ymax>
		</bndbox>
	</object>
	<object>
		<name>head</name>
		<pose>Unspecified</pose>
		<truncated>0</truncated>
		<difficult>0</difficult>
		<bndbox>
			<xmin>71</xmin>
			<ymin>94</ymin>
			<xmax>108</xmax>
			<ymax>137</ymax>
		</bndbox>
	</object>
</annotation>
